[{"13":{}},{"6":{"Value":"Microsoft.DataShare/accounts"}},{"6":{"Value":"2020-09-01"}},{"2":{"Name":"Microsoft.DataShare/accounts","Properties":{"id":{"Type":0,"Flags":10,"Description":"The resource id"},"name":{"Type":0,"Flags":9,"Description":"The resource name"},"type":{"Type":1,"Flags":10,"Description":"The resource type"},"apiVersion":{"Type":2,"Flags":10,"Description":"The resource api version"},"identity":{"Type":4,"Flags":1,"Description":"Identity Info on the Account"},"properties":{"Type":7,"Flags":0,"Description":"Properties on the account"},"location":{"Type":0,"Flags":0,"Description":"Location of the azure resource."},"tags":{"Type":14,"Flags":0,"Description":"Tags on the azure resource."},"systemData":{"Type":15,"Flags":2,"Description":"System Data of the Azure resource."}}}},{"2":{"Name":"Identity","Properties":{"principalId":{"Type":0,"Flags":2,"Description":"service principal Id"},"tenantId":{"Type":0,"Flags":2,"Description":"Tenant Id"},"type":{"Type":6,"Flags":0,"Description":"Identity Type"}}}},{"6":{"Value":"SystemAssigned"}},{"5":{"Elements":[5,0]}},{"2":{"Name":"AccountProperties","Properties":{"createdAt":{"Type":0,"Flags":2,"Description":"Time at which the account was created."},"provisioningState":{"Type":13,"Flags":2,"Description":"Provisioning state of the Account"},"userEmail":{"Type":0,"Flags":2,"Description":"Email of the user who created the resource"},"userName":{"Type":0,"Flags":2,"Description":"Name of the user who created the resource"}}}},{"6":{"Value":"Succeeded"}},{"6":{"Value":"Creating"}},{"6":{"Value":"Deleting"}},{"6":{"Value":"Moving"}},{"6":{"Value":"Failed"}},{"5":{"Elements":[8,9,10,11,12,0]}},{"2":{"Name":"DefaultDtoTags","Properties":{},"AdditionalProperties":0}},{"2":{"Name":"SystemData","Properties":{"createdAt":{"Type":0,"Flags":0,"Description":"The timestamp of resource creation (UTC)."},"createdBy":{"Type":0,"Flags":0,"Description":"The identity that created the resource."},"createdByType":{"Type":20,"Flags":0,"Description":"The type of identity that created the resource."},"lastModifiedAt":{"Type":0,"Flags":0,"Description":"The type of identity that last modified the resource."},"lastModifiedBy":{"Type":0,"Flags":0,"Description":"The identity that last modified the resource."},"lastModifiedByType":{"Type":25,"Flags":0,"Description":"The type of identity that last modified the resource."}}}},{"6":{"Value":"User"}},{"6":{"Value":"Application"}},{"6":{"Value":"ManagedIdentity"}},{"6":{"Value":"Key"}},{"5":{"Elements":[16,17,18,19,0]}},{"6":{"Value":"User"}},{"6":{"Value":"Application"}},{"6":{"Value":"ManagedIdentity"}},{"6":{"Value":"Key"}},{"5":{"Elements":[21,22,23,24,0]}},{"4":{"Name":"Microsoft.DataShare/accounts@2020-09-01","ScopeType":8,"Body":3,"Flags":0}},{"6":{"Value":"Microsoft.DataShare/accounts/shares/dataSets"}},{"6":{"Value":"2020-09-01"}},{"7":{"Name":"Microsoft.DataShare/accounts/shares/dataSets","Discriminator":"kind","BaseProperties":{"id":{"Type":0,"Flags":10,"Description":"The resource id"},"name":{"Type":0,"Flags":9,"Description":"The resource name"},"type":{"Type":27,"Flags":10,"Description":"The resource type"},"apiVersion":{"Type":28,"Flags":10,"Description":"The resource api version"},"systemData":{"Type":15,"Flags":2,"Description":"System Data of the Azure resource."}},"Elements":{"AdlsGen1File":30,"AdlsGen1Folder":33,"AdlsGen2File":36,"AdlsGen2FileSystem":39,"AdlsGen2Folder":42,"Blob":45,"BlobFolder":48,"Container":51,"KustoCluster":54,"KustoDatabase":63,"SqlDBTable":72,"SqlDWTable":75,"SynapseWorkspaceSqlPoolTable":78}}},{"2":{"Name":"AdlsGen1FileDataSet","Properties":{"properties":{"Type":31,"Flags":1,"Description":"ADLS Gen 1 file data set properties."},"kind":{"Type":32,"Flags":1,"Description":"Kind of data set."}}}},{"2":{"Name":"AdlsGen1FileProperties","Properties":{"accountName":{"Type":0,"Flags":1,"Description":"The ADLS account name."},"dataSetId":{"Type":0,"Flags":2,"Description":"Unique id for identifying a data set resource"},"fileName":{"Type":0,"Flags":1,"Description":"The file name in the ADLS account."},"folderPath":{"Type":0,"Flags":1,"Description":"The folder path within the ADLS account."},"resourceGroup":{"Type":0,"Flags":1,"Description":"Resource group of ADLS account."},"subscriptionId":{"Type":0,"Flags":1,"Description":"Subscription id of ADLS account."}}}},{"6":{"Value":"AdlsGen1File"}},{"2":{"Name":"AdlsGen1FolderDataSet","Properties":{"properties":{"Type":34,"Flags":1,"Description":"ADLS Gen 1 folder data set properties."},"kind":{"Type":35,"Flags":1,"Description":"Kind of data set."}}}},{"2":{"Name":"AdlsGen1FolderProperties","Properties":{"accountName":{"Type":0,"Flags":1,"Description":"The ADLS account name."},"dataSetId":{"Type":0,"Flags":2,"Description":"Unique id for identifying a data set resource"},"folderPath":{"Type":0,"Flags":1,"Description":"The folder path within the ADLS account."},"resourceGroup":{"Type":0,"Flags":1,"Description":"Resource group of ADLS account."},"subscriptionId":{"Type":0,"Flags":1,"Description":"Subscription id of ADLS account."}}}},{"6":{"Value":"AdlsGen1Folder"}},{"2":{"Name":"AdlsGen2FileDataSet","Properties":{"properties":{"Type":37,"Flags":1,"Description":"ADLS Gen 2 file data set properties."},"kind":{"Type":38,"Flags":1,"Description":"Kind of data set."}}}},{"2":{"Name":"AdlsGen2FileProperties","Properties":{"dataSetId":{"Type":0,"Flags":2,"Description":"Unique id for identifying a data set resource"},"filePath":{"Type":0,"Flags":1,"Description":"File path within the file system."},"fileSystem":{"Type":0,"Flags":1,"Description":"File system to which the file belongs."},"resourceGroup":{"Type":0,"Flags":1,"Description":"Resource group of storage account"},"storageAccountName":{"Type":0,"Flags":1,"Description":"Storage account name of the source data set"},"subscriptionId":{"Type":0,"Flags":1,"Description":"Subscription id of storage account"}}}},{"6":{"Value":"AdlsGen2File"}},{"2":{"Name":"AdlsGen2FileSystemDataSet","Properties":{"properties":{"Type":40,"Flags":1,"Description":"ADLS Gen 2 file system data set properties."},"kind":{"Type":41,"Flags":1,"Description":"Kind of data set."}}}},{"2":{"Name":"AdlsGen2FileSystemProperties","Properties":{"dataSetId":{"Type":0,"Flags":2,"Description":"Unique id for identifying a data set resource"},"fileSystem":{"Type":0,"Flags":1,"Description":"The file system name."},"resourceGroup":{"Type":0,"Flags":1,"Description":"Resource group of storage account"},"storageAccountName":{"Type":0,"Flags":1,"Description":"Storage account name of the source data set"},"subscriptionId":{"Type":0,"Flags":1,"Description":"Subscription id of storage account"}}}},{"6":{"Value":"AdlsGen2FileSystem"}},{"2":{"Name":"AdlsGen2FolderDataSet","Properties":{"properties":{"Type":43,"Flags":1,"Description":"ADLS Gen 2 folder data set properties."},"kind":{"Type":44,"Flags":1,"Description":"Kind of data set."}}}},{"2":{"Name":"AdlsGen2FolderProperties","Properties":{"dataSetId":{"Type":0,"Flags":2,"Description":"Unique id for identifying a data set resource"},"fileSystem":{"Type":0,"Flags":1,"Description":"File system to which the folder belongs."},"folderPath":{"Type":0,"Flags":1,"Description":"Folder path within the file system."},"resourceGroup":{"Type":0,"Flags":1,"Description":"Resource group of storage account"},"storageAccountName":{"Type":0,"Flags":1,"Description":"Storage account name of the source data set"},"subscriptionId":{"Type":0,"Flags":1,"Description":"Subscription id of storage account"}}}},{"6":{"Value":"AdlsGen2Folder"}},{"2":{"Name":"BlobDataSet","Properties":{"properties":{"Type":46,"Flags":1,"Description":"Blob data set properties."},"kind":{"Type":47,"Flags":1,"Description":"Kind of data set."}}}},{"2":{"Name":"BlobProperties","Properties":{"containerName":{"Type":0,"Flags":1,"Description":"Container that has the file path."},"dataSetId":{"Type":0,"Flags":2,"Description":"Unique id for identifying a data set resource"},"filePath":{"Type":0,"Flags":1,"Description":"File path within the source data set"},"resourceGroup":{"Type":0,"Flags":1,"Description":"Resource group of storage account"},"storageAccountName":{"Type":0,"Flags":1,"Description":"Storage account name of the source data set"},"subscriptionId":{"Type":0,"Flags":1,"Description":"Subscription id of storage account"}}}},{"6":{"Value":"Blob"}},{"2":{"Name":"BlobFolderDataSet","Properties":{"properties":{"Type":49,"Flags":1,"Description":"Blob folder data set properties."},"kind":{"Type":50,"Flags":1,"Description":"Kind of data set."}}}},{"2":{"Name":"BlobFolderProperties","Properties":{"containerName":{"Type":0,"Flags":1,"Description":"Container that has the file path."},"dataSetId":{"Type":0,"Flags":2,"Description":"Unique id for identifying a data set resource"},"prefix":{"Type":0,"Flags":1,"Description":"Prefix for blob folder"},"resourceGroup":{"Type":0,"Flags":1,"Description":"Resource group of storage account"},"storageAccountName":{"Type":0,"Flags":1,"Description":"Storage account name of the source data set"},"subscriptionId":{"Type":0,"Flags":1,"Description":"Subscription id of storage account"}}}},{"6":{"Value":"BlobFolder"}},{"2":{"Name":"BlobContainerDataSet","Properties":{"properties":{"Type":52,"Flags":1,"Description":"Blob container data set properties."},"kind":{"Type":53,"Flags":1,"Description":"Kind of data set."}}}},{"2":{"Name":"BlobContainerProperties","Properties":{"containerName":{"Type":0,"Flags":1,"Description":"BLOB Container name."},"dataSetId":{"Type":0,"Flags":2,"Description":"Unique id for identifying a data set resource"},"resourceGroup":{"Type":0,"Flags":1,"Description":"Resource group of storage account"},"storageAccountName":{"Type":0,"Flags":1,"Description":"Storage account name of the source data set"},"subscriptionId":{"Type":0,"Flags":1,"Description":"Subscription id of storage account"}}}},{"6":{"Value":"Container"}},{"2":{"Name":"KustoClusterDataSet","Properties":{"properties":{"Type":55,"Flags":1,"Description":"Kusto cluster data set properties."},"kind":{"Type":62,"Flags":1,"Description":"Kind of data set."}}}},{"2":{"Name":"KustoClusterDataSetProperties","Properties":{"dataSetId":{"Type":0,"Flags":2,"Description":"Unique id for identifying a data set resource"},"kustoClusterResourceId":{"Type":0,"Flags":1,"Description":"Resource id of the kusto cluster."},"location":{"Type":0,"Flags":2,"Description":"Location of the kusto cluster."},"provisioningState":{"Type":61,"Flags":2,"Description":"Provisioning state of the kusto cluster data set."}}}},{"6":{"Value":"Succeeded"}},{"6":{"Value":"Creating"}},{"6":{"Value":"Deleting"}},{"6":{"Value":"Moving"}},{"6":{"Value":"Failed"}},{"5":{"Elements":[56,57,58,59,60,0]}},{"6":{"Value":"KustoCluster"}},{"2":{"Name":"KustoDatabaseDataSet","Properties":{"properties":{"Type":64,"Flags":1,"Description":"Kusto database data set properties."},"kind":{"Type":71,"Flags":1,"Description":"Kind of data set."}}}},{"2":{"Name":"KustoDatabaseDataSetProperties","Properties":{"dataSetId":{"Type":0,"Flags":2,"Description":"Unique id for identifying a data set resource"},"kustoDatabaseResourceId":{"Type":0,"Flags":1,"Description":"Resource id of the kusto database."},"location":{"Type":0,"Flags":2,"Description":"Location of the kusto cluster."},"provisioningState":{"Type":70,"Flags":2,"Description":"Provisioning state of the kusto database data set."}}}},{"6":{"Value":"Succeeded"}},{"6":{"Value":"Creating"}},{"6":{"Value":"Deleting"}},{"6":{"Value":"Moving"}},{"6":{"Value":"Failed"}},{"5":{"Elements":[65,66,67,68,69,0]}},{"6":{"Value":"KustoDatabase"}},{"2":{"Name":"SqlDBTableDataSet","Properties":{"properties":{"Type":73,"Flags":0,"Description":"SQL DB table data set properties."},"kind":{"Type":74,"Flags":1,"Description":"Kind of data set."}}}},{"2":{"Name":"SqlDBTableProperties","Properties":{"databaseName":{"Type":0,"Flags":1,"Description":"Database name of the source data set"},"dataSetId":{"Type":0,"Flags":2,"Description":"Unique id for identifying a data set resource"},"schemaName":{"Type":0,"Flags":1,"Description":"Schema of the table. Default value is dbo."},"sqlServerResourceId":{"Type":0,"Flags":1,"Description":"Resource id of SQL server"},"tableName":{"Type":0,"Flags":1,"Description":"SQL DB table name."}}}},{"6":{"Value":"SqlDBTable"}},{"2":{"Name":"SqlDWTableDataSet","Properties":{"properties":{"Type":76,"Flags":0,"Description":"SQL DW table data set properties."},"kind":{"Type":77,"Flags":1,"Description":"Kind of data set."}}}},{"2":{"Name":"SqlDWTableProperties","Properties":{"dataSetId":{"Type":0,"Flags":2,"Description":"Unique id for identifying a data set resource"},"dataWarehouseName":{"Type":0,"Flags":1,"Description":"DataWarehouse name of the source data set"},"schemaName":{"Type":0,"Flags":1,"Description":"Schema of the table. Default value is dbo."},"sqlServerResourceId":{"Type":0,"Flags":1,"Description":"Resource id of SQL server"},"tableName":{"Type":0,"Flags":1,"Description":"SQL DW table name."}}}},{"6":{"Value":"SqlDWTable"}},{"2":{"Name":"SynapseWorkspaceSqlPoolTableDataSet","Properties":{"properties":{"Type":79,"Flags":1,"Description":"Synapse Workspace Sql Pool Table data set properties."},"kind":{"Type":80,"Flags":1,"Description":"Kind of data set."}}}},{"2":{"Name":"SynapseWorkspaceSqlPoolTableDataSetProperties","Properties":{"dataSetId":{"Type":0,"Flags":2,"Description":"Unique id for identifying a data set resource"},"synapseWorkspaceSqlPoolTableResourceId":{"Type":0,"Flags":1,"Description":"Resource id of the Synapse Workspace SQL Pool Table"}}}},{"6":{"Value":"SynapseWorkspaceSqlPoolTable"}},{"4":{"Name":"Microsoft.DataShare/accounts/shares/dataSets@2020-09-01","ScopeType":8,"Body":29,"Flags":0}},{"6":{"Value":"Microsoft.DataShare/accounts/shareSubscriptions/dataSetMappings"}},{"6":{"Value":"2020-09-01"}},{"7":{"Name":"Microsoft.DataShare/accounts/shareSubscriptions/dataSetMappings","Discriminator":"kind","BaseProperties":{"id":{"Type":0,"Flags":10,"Description":"The resource id"},"name":{"Type":0,"Flags":9,"Description":"The resource name"},"type":{"Type":82,"Flags":10,"Description":"The resource type"},"apiVersion":{"Type":83,"Flags":10,"Description":"The resource api version"},"systemData":{"Type":15,"Flags":2,"Description":"System Data of the Azure resource."}},"Elements":{"AdlsGen2File":85,"AdlsGen2FileSystem":100,"AdlsGen2Folder":112,"Blob":124,"BlobFolder":139,"Container":151,"KustoCluster":163,"KustoDatabase":175,"SqlDBTable":187,"SqlDWTable":199,"SynapseWorkspaceSqlPoolTable":211}}},{"2":{"Name":"AdlsGen2FileDataSetMapping","Properties":{"properties":{"Type":86,"Flags":1,"Description":"ADLS Gen2 file data set mapping properties."},"kind":{"Type":99,"Flags":1,"Description":"Kind of data set mapping."}}}},{"2":{"Name":"AdlsGen2FileDataSetMappingProperties","Properties":{"dataSetId":{"Type":0,"Flags":1,"Description":"The id of the source data set."},"dataSetMappingStatus":{"Type":89,"Flags":2,"Description":"Gets the status of the data set mapping."},"filePath":{"Type":0,"Flags":1,"Description":"File path within the file system."},"fileSystem":{"Type":0,"Flags":1,"Description":"File system to which the file belongs."},"outputType":{"Type":92,"Flags":0,"Description":"Type of output file"},"provisioningState":{"Type":98,"Flags":2,"Description":"Provisioning state of the data set mapping."},"resourceGroup":{"Type":0,"Flags":1,"Description":"Resource group of storage account."},"storageAccountName":{"Type":0,"Flags":1,"Description":"Storage account name of the source data set."},"subscriptionId":{"Type":0,"Flags":1,"Description":"Subscription id of storage account."}}}},{"6":{"Value":"Ok"}},{"6":{"Value":"Broken"}},{"5":{"Elements":[87,88,0]}},{"6":{"Value":"Csv"}},{"6":{"Value":"Parquet"}},{"5":{"Elements":[90,91,0]}},{"6":{"Value":"Succeeded"}},{"6":{"Value":"Creating"}},{"6":{"Value":"Deleting"}},{"6":{"Value":"Moving"}},{"6":{"Value":"Failed"}},{"5":{"Elements":[93,94,95,96,97,0]}},{"6":{"Value":"AdlsGen2File"}},{"2":{"Name":"AdlsGen2FileSystemDataSetMapping","Properties":{"properties":{"Type":101,"Flags":1,"Description":"ADLS Gen2 file system data set mapping properties."},"kind":{"Type":111,"Flags":1,"Description":"Kind of data set mapping."}}}},{"2":{"Name":"AdlsGen2FileSystemDataSetMappingProperties","Properties":{"dataSetId":{"Type":0,"Flags":1,"Description":"The id of the source data set."},"dataSetMappingStatus":{"Type":104,"Flags":2,"Description":"Gets the status of the data set mapping."},"fileSystem":{"Type":0,"Flags":1,"Description":"The file system name."},"provisioningState":{"Type":110,"Flags":2,"Description":"Provisioning state of the data set mapping."},"resourceGroup":{"Type":0,"Flags":1,"Description":"Resource group of storage account."},"storageAccountName":{"Type":0,"Flags":1,"Description":"Storage account name of the source data set."},"subscriptionId":{"Type":0,"Flags":1,"Description":"Subscription id of storage account."}}}},{"6":{"Value":"Ok"}},{"6":{"Value":"Broken"}},{"5":{"Elements":[102,103,0]}},{"6":{"Value":"Succeeded"}},{"6":{"Value":"Creating"}},{"6":{"Value":"Deleting"}},{"6":{"Value":"Moving"}},{"6":{"Value":"Failed"}},{"5":{"Elements":[105,106,107,108,109,0]}},{"6":{"Value":"AdlsGen2FileSystem"}},{"2":{"Name":"AdlsGen2FolderDataSetMapping","Properties":{"properties":{"Type":113,"Flags":1,"Description":"ADLS Gen2 folder data set mapping properties."},"kind":{"Type":123,"Flags":1,"Description":"Kind of data set mapping."}}}},{"2":{"Name":"AdlsGen2FolderDataSetMappingProperties","Properties":{"dataSetId":{"Type":0,"Flags":1,"Description":"The id of the source data set."},"dataSetMappingStatus":{"Type":116,"Flags":2,"Description":"Gets the status of the data set mapping."},"fileSystem":{"Type":0,"Flags":1,"Description":"File system to which the folder belongs."},"folderPath":{"Type":0,"Flags":1,"Description":"Folder path within the file system."},"provisioningState":{"Type":122,"Flags":2,"Description":"Provisioning state of the data set mapping."},"resourceGroup":{"Type":0,"Flags":1,"Description":"Resource group of storage account."},"storageAccountName":{"Type":0,"Flags":1,"Description":"Storage account name of the source data set."},"subscriptionId":{"Type":0,"Flags":1,"Description":"Subscription id of storage account."}}}},{"6":{"Value":"Ok"}},{"6":{"Value":"Broken"}},{"5":{"Elements":[114,115,0]}},{"6":{"Value":"Succeeded"}},{"6":{"Value":"Creating"}},{"6":{"Value":"Deleting"}},{"6":{"Value":"Moving"}},{"6":{"Value":"Failed"}},{"5":{"Elements":[117,118,119,120,121,0]}},{"6":{"Value":"AdlsGen2Folder"}},{"2":{"Name":"BlobDataSetMapping","Properties":{"properties":{"Type":125,"Flags":1,"Description":"Blob data set mapping properties."},"kind":{"Type":138,"Flags":1,"Description":"Kind of data set mapping."}}}},{"2":{"Name":"BlobMappingProperties","Properties":{"containerName":{"Type":0,"Flags":1,"Description":"Container that has the file path."},"dataSetId":{"Type":0,"Flags":1,"Description":"The id of the source data set."},"dataSetMappingStatus":{"Type":128,"Flags":2,"Description":"Gets the status of the data set mapping."},"filePath":{"Type":0,"Flags":1,"Description":"File path within the source data set"},"outputType":{"Type":131,"Flags":0,"Description":"File output type"},"provisioningState":{"Type":137,"Flags":2,"Description":"Provisioning state of the data set mapping."},"resourceGroup":{"Type":0,"Flags":1,"Description":"Resource group of storage account."},"storageAccountName":{"Type":0,"Flags":1,"Description":"Storage account name of the source data set."},"subscriptionId":{"Type":0,"Flags":1,"Description":"Subscription id of storage account."}}}},{"6":{"Value":"Ok"}},{"6":{"Value":"Broken"}},{"5":{"Elements":[126,127,0]}},{"6":{"Value":"Csv"}},{"6":{"Value":"Parquet"}},{"5":{"Elements":[129,130,0]}},{"6":{"Value":"Succeeded"}},{"6":{"Value":"Creating"}},{"6":{"Value":"Deleting"}},{"6":{"Value":"Moving"}},{"6":{"Value":"Failed"}},{"5":{"Elements":[132,133,134,135,136,0]}},{"6":{"Value":"Blob"}},{"2":{"Name":"BlobFolderDataSetMapping","Properties":{"properties":{"Type":140,"Flags":1,"Description":"Blob folder data set mapping properties."},"kind":{"Type":150,"Flags":1,"Description":"Kind of data set mapping."}}}},{"2":{"Name":"BlobFolderMappingProperties","Properties":{"containerName":{"Type":0,"Flags":1,"Description":"Container that has the file path."},"dataSetId":{"Type":0,"Flags":1,"Description":"The id of the source data set."},"dataSetMappingStatus":{"Type":143,"Flags":2,"Description":"Gets the status of the data set mapping."},"prefix":{"Type":0,"Flags":1,"Description":"Prefix for blob folder"},"provisioningState":{"Type":149,"Flags":2,"Description":"Provisioning state of the data set mapping."},"resourceGroup":{"Type":0,"Flags":1,"Description":"Resource group of storage account."},"storageAccountName":{"Type":0,"Flags":1,"Description":"Storage account name of the source data set."},"subscriptionId":{"Type":0,"Flags":1,"Description":"Subscription id of storage account."}}}},{"6":{"Value":"Ok"}},{"6":{"Value":"Broken"}},{"5":{"Elements":[141,142,0]}},{"6":{"Value":"Succeeded"}},{"6":{"Value":"Creating"}},{"6":{"Value":"Deleting"}},{"6":{"Value":"Moving"}},{"6":{"Value":"Failed"}},{"5":{"Elements":[144,145,146,147,148,0]}},{"6":{"Value":"BlobFolder"}},{"2":{"Name":"BlobContainerDataSetMapping","Properties":{"properties":{"Type":152,"Flags":1,"Description":"Blob container data set mapping properties."},"kind":{"Type":162,"Flags":1,"Description":"Kind of data set mapping."}}}},{"2":{"Name":"BlobContainerMappingProperties","Properties":{"containerName":{"Type":0,"Flags":1,"Description":"BLOB Container name."},"dataSetId":{"Type":0,"Flags":1,"Description":"The id of the source data set."},"dataSetMappingStatus":{"Type":155,"Flags":2,"Description":"Gets the status of the data set mapping."},"provisioningState":{"Type":161,"Flags":2,"Description":"Provisioning state of the data set mapping."},"resourceGroup":{"Type":0,"Flags":1,"Description":"Resource group of storage account."},"storageAccountName":{"Type":0,"Flags":1,"Description":"Storage account name of the source data set."},"subscriptionId":{"Type":0,"Flags":1,"Description":"Subscription id of storage account."}}}},{"6":{"Value":"Ok"}},{"6":{"Value":"Broken"}},{"5":{"Elements":[153,154,0]}},{"6":{"Value":"Succeeded"}},{"6":{"Value":"Creating"}},{"6":{"Value":"Deleting"}},{"6":{"Value":"Moving"}},{"6":{"Value":"Failed"}},{"5":{"Elements":[156,157,158,159,160,0]}},{"6":{"Value":"Container"}},{"2":{"Name":"KustoClusterDataSetMapping","Properties":{"properties":{"Type":164,"Flags":1,"Description":"Kusto cluster data set mapping properties."},"kind":{"Type":174,"Flags":1,"Description":"Kind of data set mapping."}}}},{"2":{"Name":"KustoClusterDataSetMappingProperties","Properties":{"dataSetId":{"Type":0,"Flags":1,"Description":"The id of the source data set."},"dataSetMappingStatus":{"Type":167,"Flags":2,"Description":"Gets the status of the data set mapping."},"kustoClusterResourceId":{"Type":0,"Flags":1,"Description":"Resource id of the sink kusto cluster."},"location":{"Type":0,"Flags":2,"Description":"Location of the sink kusto cluster."},"provisioningState":{"Type":173,"Flags":2,"Description":"Provisioning state of the data set mapping."}}}},{"6":{"Value":"Ok"}},{"6":{"Value":"Broken"}},{"5":{"Elements":[165,166,0]}},{"6":{"Value":"Succeeded"}},{"6":{"Value":"Creating"}},{"6":{"Value":"Deleting"}},{"6":{"Value":"Moving"}},{"6":{"Value":"Failed"}},{"5":{"Elements":[168,169,170,171,172,0]}},{"6":{"Value":"KustoCluster"}},{"2":{"Name":"KustoDatabaseDataSetMapping","Properties":{"properties":{"Type":176,"Flags":1,"Description":"Kusto database data set mapping properties."},"kind":{"Type":186,"Flags":1,"Description":"Kind of data set mapping."}}}},{"2":{"Name":"KustoDatabaseDataSetMappingProperties","Properties":{"dataSetId":{"Type":0,"Flags":1,"Description":"The id of the source data set."},"dataSetMappingStatus":{"Type":179,"Flags":2,"Description":"Gets the status of the data set mapping."},"kustoClusterResourceId":{"Type":0,"Flags":1,"Description":"Resource id of the sink kusto cluster."},"location":{"Type":0,"Flags":2,"Description":"Location of the sink kusto cluster."},"provisioningState":{"Type":185,"Flags":2,"Description":"Provisioning state of the data set mapping."}}}},{"6":{"Value":"Ok"}},{"6":{"Value":"Broken"}},{"5":{"Elements":[177,178,0]}},{"6":{"Value":"Succeeded"}},{"6":{"Value":"Creating"}},{"6":{"Value":"Deleting"}},{"6":{"Value":"Moving"}},{"6":{"Value":"Failed"}},{"5":{"Elements":[180,181,182,183,184,0]}},{"6":{"Value":"KustoDatabase"}},{"2":{"Name":"SqlDBTableDataSetMapping","Properties":{"properties":{"Type":188,"Flags":1,"Description":"Sql DB data set mapping properties."},"kind":{"Type":198,"Flags":1,"Description":"Kind of data set mapping."}}}},{"2":{"Name":"SqlDBTableDataSetMappingProperties","Properties":{"databaseName":{"Type":0,"Flags":1,"Description":"DatabaseName name of the sink data set"},"dataSetId":{"Type":0,"Flags":1,"Description":"The id of the source data set."},"dataSetMappingStatus":{"Type":191,"Flags":2,"Description":"Gets the status of the data set mapping."},"provisioningState":{"Type":197,"Flags":2,"Description":"Provisioning state of the data set mapping."},"schemaName":{"Type":0,"Flags":1,"Description":"Schema of the table. Default value is dbo."},"sqlServerResourceId":{"Type":0,"Flags":1,"Description":"Resource id of SQL server"},"tableName":{"Type":0,"Flags":1,"Description":"SQL DB table name."}}}},{"6":{"Value":"Ok"}},{"6":{"Value":"Broken"}},{"5":{"Elements":[189,190,0]}},{"6":{"Value":"Succeeded"}},{"6":{"Value":"Creating"}},{"6":{"Value":"Deleting"}},{"6":{"Value":"Moving"}},{"6":{"Value":"Failed"}},{"5":{"Elements":[192,193,194,195,196,0]}},{"6":{"Value":"SqlDBTable"}},{"2":{"Name":"SqlDWTableDataSetMapping","Properties":{"properties":{"Type":200,"Flags":1,"Description":"Sql DW data set mapping properties."},"kind":{"Type":210,"Flags":1,"Description":"Kind of data set mapping."}}}},{"2":{"Name":"SqlDWTableDataSetMappingProperties","Properties":{"dataSetId":{"Type":0,"Flags":1,"Description":"The id of the source data set."},"dataSetMappingStatus":{"Type":203,"Flags":2,"Description":"Gets the status of the data set mapping."},"dataWarehouseName":{"Type":0,"Flags":1,"Description":"DataWarehouse name of the source data set"},"provisioningState":{"Type":209,"Flags":2,"Description":"Provisioning state of the data set mapping."},"schemaName":{"Type":0,"Flags":1,"Description":"Schema of the table. Default value is dbo."},"sqlServerResourceId":{"Type":0,"Flags":1,"Description":"Resource id of SQL server"},"tableName":{"Type":0,"Flags":1,"Description":"SQL DW table name."}}}},{"6":{"Value":"Ok"}},{"6":{"Value":"Broken"}},{"5":{"Elements":[201,202,0]}},{"6":{"Value":"Succeeded"}},{"6":{"Value":"Creating"}},{"6":{"Value":"Deleting"}},{"6":{"Value":"Moving"}},{"6":{"Value":"Failed"}},{"5":{"Elements":[204,205,206,207,208,0]}},{"6":{"Value":"SqlDWTable"}},{"2":{"Name":"SynapseWorkspaceSqlPoolTableDataSetMapping","Properties":{"properties":{"Type":212,"Flags":1,"Description":"A Synapse Workspace Sql Pool Table data set mapping properties."},"kind":{"Type":222,"Flags":1,"Description":"Kind of data set mapping."}}}},{"2":{"Name":"SynapseWorkspaceSqlPoolTableDataSetMappingProperties","Properties":{"dataSetId":{"Type":0,"Flags":1,"Description":"The id of the source data set."},"dataSetMappingStatus":{"Type":215,"Flags":2,"Description":"Gets the status of the data set mapping."},"provisioningState":{"Type":221,"Flags":2,"Description":"Provisioning state of the data set mapping."},"synapseWorkspaceSqlPoolTableResourceId":{"Type":0,"Flags":1,"Description":"Resource id of the Synapse Workspace SQL Pool Table"}}}},{"6":{"Value":"Ok"}},{"6":{"Value":"Broken"}},{"5":{"Elements":[213,214,0]}},{"6":{"Value":"Succeeded"}},{"6":{"Value":"Creating"}},{"6":{"Value":"Deleting"}},{"6":{"Value":"Moving"}},{"6":{"Value":"Failed"}},{"5":{"Elements":[216,217,218,219,220,0]}},{"6":{"Value":"SynapseWorkspaceSqlPoolTable"}},{"4":{"Name":"Microsoft.DataShare/accounts/shareSubscriptions/dataSetMappings@2020-09-01","ScopeType":8,"Body":84,"Flags":0}},{"6":{"Value":"Microsoft.DataShare/accounts/shares/invitations"}},{"6":{"Value":"2020-09-01"}},{"2":{"Name":"Microsoft.DataShare/accounts/shares/invitations","Properties":{"id":{"Type":0,"Flags":10,"Description":"The resource id"},"name":{"Type":0,"Flags":9,"Description":"The resource name"},"type":{"Type":224,"Flags":10,"Description":"The resource type"},"apiVersion":{"Type":225,"Flags":10,"Description":"The resource api version"},"properties":{"Type":227,"Flags":0,"Description":"Properties on the Invitation"},"systemData":{"Type":15,"Flags":2,"Description":"System Data of the Azure resource."}}}},{"2":{"Name":"InvitationProperties","Properties":{"expirationDate":{"Type":0,"Flags":0,"Description":"The expiration date for the invitation and share subscription."},"invitationId":{"Type":0,"Flags":2,"Description":"unique invitation id"},"invitationStatus":{"Type":232,"Flags":2,"Description":"The status of the invitation."},"respondedAt":{"Type":0,"Flags":2,"Description":"The time the recipient responded to the invitation."},"sentAt":{"Type":0,"Flags":2,"Description":"Gets the time at which the invitation was sent."},"targetActiveDirectoryId":{"Type":0,"Flags":0,"Description":"The target Azure AD Id. Can't be combined with email."},"targetEmail":{"Type":0,"Flags":0,"Description":"The email the invitation is directed to."},"targetObjectId":{"Type":0,"Flags":0,"Description":"The target user or application Id that invitation is being sent to.\r\nMust be specified along TargetActiveDirectoryId. This enables sending\r\ninvitations to specific users or applications in an AD tenant."},"userEmail":{"Type":0,"Flags":2,"Description":"Email of the user who created the resource"},"userName":{"Type":0,"Flags":2,"Description":"Name of the user who created the resource"}}}},{"6":{"Value":"Pending"}},{"6":{"Value":"Accepted"}},{"6":{"Value":"Rejected"}},{"6":{"Value":"Withdrawn"}},{"5":{"Elements":[228,229,230,231,0]}},{"4":{"Name":"Microsoft.DataShare/accounts/shares/invitations@2020-09-01","ScopeType":8,"Body":226,"Flags":0}},{"6":{"Value":"Microsoft.DataShare/accounts/shares"}},{"6":{"Value":"2020-09-01"}},{"2":{"Name":"Microsoft.DataShare/accounts/shares","Properties":{"id":{"Type":0,"Flags":10,"Description":"The resource id"},"name":{"Type":0,"Flags":9,"Description":"The resource name"},"type":{"Type":234,"Flags":10,"Description":"The resource type"},"apiVersion":{"Type":235,"Flags":10,"Description":"The resource api version"},"properties":{"Type":237,"Flags":0,"Description":"Properties on the share"},"systemData":{"Type":15,"Flags":2,"Description":"System Data of the Azure resource."}}}},{"2":{"Name":"ShareProperties","Properties":{"createdAt":{"Type":0,"Flags":2,"Description":"Time at which the share was created."},"description":{"Type":0,"Flags":0,"Description":"Share description."},"provisioningState":{"Type":243,"Flags":2,"Description":"Gets or sets the provisioning state"},"shareKind":{"Type":246,"Flags":0,"Description":"Share kind."},"terms":{"Type":0,"Flags":0,"Description":"Share terms."},"userEmail":{"Type":0,"Flags":2,"Description":"Email of the user who created the resource"},"userName":{"Type":0,"Flags":2,"Description":"Name of the user who created the resource"}}}},{"6":{"Value":"Succeeded"}},{"6":{"Value":"Creating"}},{"6":{"Value":"Deleting"}},{"6":{"Value":"Moving"}},{"6":{"Value":"Failed"}},{"5":{"Elements":[238,239,240,241,242,0]}},{"6":{"Value":"CopyBased"}},{"6":{"Value":"InPlace"}},{"5":{"Elements":[244,245,0]}},{"4":{"Name":"Microsoft.DataShare/accounts/shares@2020-09-01","ScopeType":8,"Body":236,"Flags":0}},{"6":{"Value":"Microsoft.DataShare/accounts/shareSubscriptions"}},{"6":{"Value":"2020-09-01"}},{"2":{"Name":"Microsoft.DataShare/accounts/shareSubscriptions","Properties":{"id":{"Type":0,"Flags":10,"Description":"The resource id"},"name":{"Type":0,"Flags":9,"Description":"The resource name"},"type":{"Type":248,"Flags":10,"Description":"The resource type"},"apiVersion":{"Type":249,"Flags":10,"Description":"The resource api version"},"properties":{"Type":251,"Flags":1,"Description":"Properties on the share subscription"},"systemData":{"Type":15,"Flags":2,"Description":"System Data of the Azure resource."}}}},{"2":{"Name":"ShareSubscriptionProperties","Properties":{"createdAt":{"Type":0,"Flags":2,"Description":"Time at which the share subscription was created."},"expirationDate":{"Type":0,"Flags":0,"Description":"The expiration date of the share subscription."},"invitationId":{"Type":0,"Flags":1,"Description":"The invitation id."},"providerEmail":{"Type":0,"Flags":2,"Description":"Email of the provider who created the resource"},"providerName":{"Type":0,"Flags":2,"Description":"Name of the provider who created the resource"},"providerTenantName":{"Type":0,"Flags":2,"Description":"Tenant name of the provider who created the resource"},"provisioningState":{"Type":257,"Flags":2,"Description":"Provisioning state of the share subscription"},"shareDescription":{"Type":0,"Flags":2,"Description":"Description of share"},"shareKind":{"Type":260,"Flags":2,"Description":"Kind of share"},"shareName":{"Type":0,"Flags":2,"Description":"Name of the share"},"shareSubscriptionStatus":{"Type":265,"Flags":2,"Description":"Gets the current status of share subscription."},"shareTerms":{"Type":0,"Flags":2,"Description":"Terms of a share"},"sourceShareLocation":{"Type":0,"Flags":1,"Description":"Source share location."},"userEmail":{"Type":0,"Flags":2,"Description":"Email of the user who created the resource"},"userName":{"Type":0,"Flags":2,"Description":"Name of the user who created the resource"}}}},{"6":{"Value":"Succeeded"}},{"6":{"Value":"Creating"}},{"6":{"Value":"Deleting"}},{"6":{"Value":"Moving"}},{"6":{"Value":"Failed"}},{"5":{"Elements":[252,253,254,255,256,0]}},{"6":{"Value":"CopyBased"}},{"6":{"Value":"InPlace"}},{"5":{"Elements":[258,259,0]}},{"6":{"Value":"Active"}},{"6":{"Value":"Revoked"}},{"6":{"Value":"SourceDeleted"}},{"6":{"Value":"Revoking"}},{"5":{"Elements":[261,262,263,264,0]}},{"4":{"Name":"Microsoft.DataShare/accounts/shareSubscriptions@2020-09-01","ScopeType":8,"Body":250,"Flags":0}},{"6":{"Value":"Microsoft.DataShare/accounts/shares/synchronizationSettings"}},{"6":{"Value":"2020-09-01"}},{"7":{"Name":"Microsoft.DataShare/accounts/shares/synchronizationSettings","Discriminator":"kind","BaseProperties":{"id":{"Type":0,"Flags":10,"Description":"The resource id"},"name":{"Type":0,"Flags":9,"Description":"The resource name"},"type":{"Type":267,"Flags":10,"Description":"The resource type"},"apiVersion":{"Type":268,"Flags":10,"Description":"The resource api version"},"systemData":{"Type":15,"Flags":2,"Description":"System Data of the Azure resource."}},"Elements":{"ScheduleBased":270}}},{"2":{"Name":"ScheduledSynchronizationSetting","Properties":{"properties":{"Type":271,"Flags":1,"Description":"Properties of scheduled synchronization"},"kind":{"Type":281,"Flags":1,"Description":"Kind of synchronization setting."}}}},{"2":{"Name":"ScheduledSynchronizationSettingProperties","Properties":{"createdAt":{"Type":0,"Flags":2,"Description":"Time at which the synchronization setting was created."},"provisioningState":{"Type":277,"Flags":2,"Description":"Gets or sets the provisioning state"},"recurrenceInterval":{"Type":280,"Flags":1,"Description":"Recurrence Interval"},"synchronizationTime":{"Type":0,"Flags":1,"Description":"Synchronization time"},"userName":{"Type":0,"Flags":2,"Description":"Name of the user who created the synchronization setting."}}}},{"6":{"Value":"Succeeded"}},{"6":{"Value":"Creating"}},{"6":{"Value":"Deleting"}},{"6":{"Value":"Moving"}},{"6":{"Value":"Failed"}},{"5":{"Elements":[272,273,274,275,276,0]}},{"6":{"Value":"Hour"}},{"6":{"Value":"Day"}},{"5":{"Elements":[278,279,0]}},{"6":{"Value":"ScheduleBased"}},{"4":{"Name":"Microsoft.DataShare/accounts/shares/synchronizationSettings@2020-09-01","ScopeType":8,"Body":269,"Flags":0}},{"6":{"Value":"Microsoft.DataShare/accounts/shareSubscriptions/triggers"}},{"6":{"Value":"2020-09-01"}},{"7":{"Name":"Microsoft.DataShare/accounts/shareSubscriptions/triggers","Discriminator":"kind","BaseProperties":{"id":{"Type":0,"Flags":10,"Description":"The resource id"},"name":{"Type":0,"Flags":9,"Description":"The resource name"},"type":{"Type":283,"Flags":10,"Description":"The resource type"},"apiVersion":{"Type":284,"Flags":10,"Description":"The resource api version"},"systemData":{"Type":15,"Flags":2,"Description":"System Data of the Azure resource."}},"Elements":{"ScheduleBased":286}}},{"2":{"Name":"ScheduledTrigger","Properties":{"properties":{"Type":287,"Flags":1,"Description":"Properties of scheduled synchronization"},"kind":{"Type":304,"Flags":1,"Description":"Kind of synchronization on trigger."}}}},{"2":{"Name":"ScheduledTriggerProperties","Properties":{"createdAt":{"Type":0,"Flags":2,"Description":"Time at which the trigger was created."},"provisioningState":{"Type":293,"Flags":2,"Description":"Gets the provisioning state"},"recurrenceInterval":{"Type":296,"Flags":1,"Description":"Recurrence Interval"},"synchronizationMode":{"Type":299,"Flags":0,"Description":"Synchronization mode"},"synchronizationTime":{"Type":0,"Flags":1,"Description":"Synchronization time"},"triggerStatus":{"Type":303,"Flags":2,"Description":"Gets the trigger state"},"userName":{"Type":0,"Flags":2,"Description":"Name of the user who created the trigger."}}}},{"6":{"Value":"Succeeded"}},{"6":{"Value":"Creating"}},{"6":{"Value":"Deleting"}},{"6":{"Value":"Moving"}},{"6":{"Value":"Failed"}},{"5":{"Elements":[288,289,290,291,292,0]}},{"6":{"Value":"Hour"}},{"6":{"Value":"Day"}},{"5":{"Elements":[294,295,0]}},{"6":{"Value":"Incremental"}},{"6":{"Value":"FullSync"}},{"5":{"Elements":[297,298,0]}},{"6":{"Value":"Active"}},{"6":{"Value":"Inactive"}},{"6":{"Value":"SourceSynchronizationSettingDeleted"}},{"5":{"Elements":[300,301,302,0]}},{"6":{"Value":"ScheduleBased"}},{"4":{"Name":"Microsoft.DataShare/accounts/shareSubscriptions/triggers@2020-09-01","ScopeType":8,"Body":285,"Flags":0}},{"6":{"Value":"Microsoft.DataShare/locations/consumerInvitations"}},{"6":{"Value":"2020-09-01"}},{"2":{"Name":"Microsoft.DataShare/locations/consumerInvitations","Properties":{"id":{"Type":0,"Flags":10,"Description":"The resource id"},"name":{"Type":0,"Flags":9,"Description":"The resource name"},"type":{"Type":306,"Flags":10,"Description":"The resource type"},"apiVersion":{"Type":307,"Flags":10,"Description":"The resource api version"},"properties":{"Type":309,"Flags":2,"Description":"Properties on the account"},"systemData":{"Type":15,"Flags":2,"Description":"System Data of the Azure resource."}}}},{"2":{"Name":"ConsumerInvitationProperties","Properties":{"dataSetCount":{"Type":310,"Flags":2,"Description":"Number of data sets in a share"},"description":{"Type":0,"Flags":2,"Description":"Description shared when the invitation was created"},"expirationDate":{"Type":0,"Flags":2,"Description":"The expiration date for the share subscription created by accepting the invitation."},"invitationId":{"Type":0,"Flags":1,"Description":"Unique id of the invitation."},"invitationStatus":{"Type":315,"Flags":2,"Description":"The status of the invitation."},"location":{"Type":0,"Flags":2,"Description":"invitation location"},"providerEmail":{"Type":0,"Flags":2,"Description":"Email of the provider who created the resource"},"providerName":{"Type":0,"Flags":2,"Description":"Name of the provider who created the resource"},"providerTenantName":{"Type":0,"Flags":2,"Description":"Tenant name of the provider who created the resource"},"respondedAt":{"Type":0,"Flags":2,"Description":"The time the recipient responded to the invitation."},"sentAt":{"Type":0,"Flags":2,"Description":"Gets the time at which the invitation was sent."},"shareName":{"Type":0,"Flags":2,"Description":"Gets the source share Name."},"termsOfUse":{"Type":0,"Flags":2,"Description":"Terms of use shared when the invitation was created"},"userEmail":{"Type":0,"Flags":2,"Description":"Email of the user who created the resource"},"userName":{"Type":0,"Flags":2,"Description":"Name of the user who created the resource"}}}},{"12":{}},{"6":{"Value":"Pending"}},{"6":{"Value":"Accepted"}},{"6":{"Value":"Rejected"}},{"6":{"Value":"Withdrawn"}},{"5":{"Elements":[311,312,313,314,0]}},{"4":{"Name":"Microsoft.DataShare/locations/consumerInvitations@2020-09-01","ScopeType":1,"Body":308,"Flags":1}},{"6":{"Value":"Microsoft.DataShare/accounts/shares/providerShareSubscriptions"}},{"6":{"Value":"2020-09-01"}},{"2":{"Name":"Microsoft.DataShare/accounts/shares/providerShareSubscriptions","Properties":{"id":{"Type":0,"Flags":10,"Description":"The resource id"},"name":{"Type":0,"Flags":9,"Description":"The resource name"},"type":{"Type":317,"Flags":10,"Description":"The resource type"},"apiVersion":{"Type":318,"Flags":10,"Description":"The resource api version"},"properties":{"Type":320,"Flags":2,"Description":"properties of providerShareSubscription"},"systemData":{"Type":15,"Flags":2,"Description":"System Data of the Azure resource."}}}},{"2":{"Name":"ProviderShareSubscriptionProperties","Properties":{"consumerEmail":{"Type":0,"Flags":2,"Description":"Email of the consumer who created the share subscription"},"consumerName":{"Type":0,"Flags":2,"Description":"Name of the consumer who created the share subscription"},"consumerTenantName":{"Type":0,"Flags":2,"Description":"Tenant name of the consumer who created the share subscription"},"createdAt":{"Type":0,"Flags":2,"Description":"created at"},"expirationDate":{"Type":0,"Flags":0,"Description":"Expiration date of the share subscription in UTC format"},"providerEmail":{"Type":0,"Flags":2,"Description":"Email of the provider who created the share"},"providerName":{"Type":0,"Flags":2,"Description":"Name of the provider who created the share"},"sharedAt":{"Type":0,"Flags":2,"Description":"Shared at"},"shareSubscriptionObjectId":{"Type":0,"Flags":2,"Description":"share Subscription Object Id"},"shareSubscriptionStatus":{"Type":325,"Flags":2,"Description":"Gets the status of share subscription"}}}},{"6":{"Value":"Active"}},{"6":{"Value":"Revoked"}},{"6":{"Value":"SourceDeleted"}},{"6":{"Value":"Revoking"}},{"5":{"Elements":[321,322,323,324,0]}},{"4":{"Name":"Microsoft.DataShare/accounts/shares/providerShareSubscriptions@2020-09-01","ScopeType":8,"Body":319,"Flags":1}},{"2":{"Name":"ShareSynchronization","Properties":{"consumerEmail":{"Type":0,"Flags":0,"Description":"Email of the user who created the synchronization"},"consumerName":{"Type":0,"Flags":0,"Description":"Name of the user who created the synchronization"},"consumerTenantName":{"Type":0,"Flags":0,"Description":"Tenant name of the consumer who created the synchronization"},"durationMs":{"Type":310,"Flags":0,"Description":"synchronization duration"},"endTime":{"Type":0,"Flags":0,"Description":"End time of synchronization"},"message":{"Type":0,"Flags":0,"Description":"message of synchronization"},"startTime":{"Type":0,"Flags":0,"Description":"start time of synchronization"},"status":{"Type":0,"Flags":0,"Description":"Raw Status"},"synchronizationId":{"Type":0,"Flags":0,"Description":"Synchronization id"},"synchronizationMode":{"Type":330,"Flags":2,"Description":"Synchronization mode"}}}},{"6":{"Value":"Incremental"}},{"6":{"Value":"FullSync"}},{"5":{"Elements":[328,329,0]}},{"2":{"Name":"SynchronizationDetailsList","Properties":{"nextLink":{"Type":0,"Flags":0,"Description":"The Url of next result page."},"value":{"Type":347,"Flags":1,"Description":"Collection of items of type DataTransferObjects."}}}},{"2":{"Name":"SynchronizationDetails","Properties":{"dataSetId":{"Type":0,"Flags":2,"Description":"Id of data set"},"dataSetType":{"Type":346,"Flags":2,"Description":"Type of the data set"},"durationMs":{"Type":310,"Flags":2,"Description":"Duration of data set level copy"},"endTime":{"Type":0,"Flags":2,"Description":"End time of data set level copy"},"filesRead":{"Type":310,"Flags":2,"Description":"The number of files read from the source data set"},"filesWritten":{"Type":310,"Flags":2,"Description":"The number of files written into the sink data set"},"message":{"Type":0,"Flags":2,"Description":"Error message if any"},"name":{"Type":0,"Flags":2,"Description":"Name of the data set"},"rowsCopied":{"Type":310,"Flags":2,"Description":"The number of files copied into the sink data set"},"rowsRead":{"Type":310,"Flags":2,"Description":"The number of rows read from the source data set."},"sizeRead":{"Type":310,"Flags":2,"Description":"The size of the data read from the source data set in bytes"},"sizeWritten":{"Type":310,"Flags":2,"Description":"The size of the data written into the sink data set in bytes"},"startTime":{"Type":0,"Flags":2,"Description":"Start time of data set level copy"},"status":{"Type":0,"Flags":2,"Description":"Raw Status"},"vCore":{"Type":310,"Flags":2,"Description":"The vCore units consumed for the data set synchronization"}}}},{"6":{"Value":"Blob"}},{"6":{"Value":"Container"}},{"6":{"Value":"BlobFolder"}},{"6":{"Value":"AdlsGen2FileSystem"}},{"6":{"Value":"AdlsGen2Folder"}},{"6":{"Value":"AdlsGen2File"}},{"6":{"Value":"AdlsGen1Folder"}},{"6":{"Value":"AdlsGen1File"}},{"6":{"Value":"KustoCluster"}},{"6":{"Value":"KustoDatabase"}},{"6":{"Value":"SqlDBTable"}},{"6":{"Value":"SqlDWTable"}},{"6":{"Value":"SynapseWorkspaceSqlPoolTable"}},{"5":{"Elements":[333,334,335,336,337,338,339,340,341,342,343,344,345,0]}},{"3":{"ItemType":332}},{"8":{"Name":"listSynchronizationDetails","ResourceType":"Microsoft.DataShare/accounts/shares","ApiVersion":"2020-09-01","Output":331,"Input":327}},{"2":{"Name":"ShareSynchronizationList","Properties":{"nextLink":{"Type":0,"Flags":0,"Description":"The Url of next result page."},"value":{"Type":350,"Flags":1,"Description":"Collection of items of type DataTransferObjects."}}}},{"3":{"ItemType":327}},{"8":{"Name":"listSynchronizations","ResourceType":"Microsoft.DataShare/accounts/shares","ApiVersion":"2020-09-01","Output":349}},{"2":{"Name":"SourceShareSynchronizationSettingList","Properties":{"nextLink":{"Type":0,"Flags":0,"Description":"The Url of next result page."},"value":{"Type":360,"Flags":1,"Description":"Collection of items of type DataTransferObjects."}}}},{"7":{"Name":"SourceShareSynchronizationSetting","Discriminator":"kind","BaseProperties":{},"Elements":{"ScheduleBased":354}}},{"2":{"Name":"ScheduledSourceSynchronizationSetting","Properties":{"properties":{"Type":355,"Flags":0,"Description":"Properties of scheduled synchronization"},"kind":{"Type":359,"Flags":1,"Description":"Kind of synchronization setting on share."}}}},{"2":{"Name":"ScheduledSourceShareSynchronizationSettingProperties","Properties":{"recurrenceInterval":{"Type":358,"Flags":0,"Description":"Recurrence Interval"},"synchronizationTime":{"Type":0,"Flags":0,"Description":"Synchronization time"}}}},{"6":{"Value":"Hour"}},{"6":{"Value":"Day"}},{"5":{"Elements":[356,357,0]}},{"6":{"Value":"ScheduleBased"}},{"3":{"ItemType":353}},{"8":{"Name":"listSourceShareSynchronizationSettings","ResourceType":"Microsoft.DataShare/accounts/shareSubscriptions","ApiVersion":"2020-09-01","Output":352}},{"2":{"Name":"ShareSubscriptionSynchronization","Properties":{"durationMs":{"Type":310,"Flags":2,"Description":"Synchronization duration"},"endTime":{"Type":0,"Flags":2,"Description":"End time of synchronization"},"message":{"Type":0,"Flags":2,"Description":"message of Synchronization"},"startTime":{"Type":0,"Flags":2,"Description":"start time of synchronization"},"status":{"Type":0,"Flags":2,"Description":"Raw Status"},"synchronizationId":{"Type":0,"Flags":1,"Description":"Synchronization id"},"synchronizationMode":{"Type":365,"Flags":2,"Description":"Synchronization Mode"}}}},{"6":{"Value":"Incremental"}},{"6":{"Value":"FullSync"}},{"5":{"Elements":[363,364,0]}},{"8":{"Name":"listSynchronizationDetails","ResourceType":"Microsoft.DataShare/accounts/shareSubscriptions","ApiVersion":"2020-09-01","Output":331,"Input":362}},{"2":{"Name":"ShareSubscriptionSynchronizationList","Properties":{"nextLink":{"Type":0,"Flags":0,"Description":"The Url of next result page."},"value":{"Type":368,"Flags":1,"Description":"Collection of items of type DataTransferObjects."}}}},{"3":{"ItemType":362}},{"8":{"Name":"listSynchronizations","ResourceType":"Microsoft.DataShare/accounts/shareSubscriptions","ApiVersion":"2020-09-01","Output":367}}]