[{"13":{}},{"6":{"Value":"Microsoft.HealthcareApis/services"}},{"6":{"Value":"2021-11-01"}},{"2":{"Name":"Microsoft.HealthcareApis/services","Properties":{"id":{"Type":0,"Flags":10,"Description":"The resource id"},"name":{"Type":0,"Flags":9,"Description":"The resource name"},"type":{"Type":1,"Flags":10,"Description":"The resource type"},"apiVersion":{"Type":2,"Flags":10,"Description":"The resource api version"},"properties":{"Type":4,"Flags":0,"Description":"The common properties of a service."},"systemData":{"Type":51,"Flags":2,"Description":"Metadata pertaining to creation and last modification of the resource."},"kind":{"Type":65,"Flags":1,"Description":"The kind of the service."},"location":{"Type":0,"Flags":1,"Description":"The resource location."},"tags":{"Type":66,"Flags":0,"Description":"The resource tags."},"etag":{"Type":0,"Flags":0,"Description":"An etag associated with the resource, used for optimistic concurrency when editing it."},"identity":{"Type":67,"Flags":0,"Description":"Setting indicating whether the service has a managed identity associated with it."}}}},{"2":{"Name":"ServicesProperties","Properties":{"provisioningState":{"Type":18,"Flags":2,"Description":"The provisioning state."},"accessPolicies":{"Type":20,"Flags":0,"Description":"The access policies of the service instance."},"cosmosDbConfiguration":{"Type":21,"Flags":0,"Description":"The settings for the Cosmos DB database backing the service."},"authenticationConfiguration":{"Type":23,"Flags":0,"Description":"The authentication configuration for the service instance."},"corsConfiguration":{"Type":25,"Flags":0,"Description":"The settings for the CORS configuration of the service instance."},"exportConfiguration":{"Type":29,"Flags":0,"Description":"The settings for the export operation of the service instance."},"privateEndpointConnections":{"Type":43,"Flags":0,"Description":"The list of private endpoint connections that are set up for this resource."},"publicNetworkAccess":{"Type":46,"Flags":0,"Description":"Control permission for data plane traffic coming from public networks while private endpoint is enabled."},"acrConfiguration":{"Type":47,"Flags":0,"Description":"The azure container registry settings used for convert data operation of the service instance."}}}},{"6":{"Value":"Deleting"}},{"6":{"Value":"Succeeded"}},{"6":{"Value":"Creating"}},{"6":{"Value":"Accepted"}},{"6":{"Value":"Verifying"}},{"6":{"Value":"Updating"}},{"6":{"Value":"Failed"}},{"6":{"Value":"Canceled"}},{"6":{"Value":"Deprovisioned"}},{"6":{"Value":"Moving"}},{"6":{"Value":"Suspended"}},{"6":{"Value":"Warned"}},{"6":{"Value":"SystemMaintenance"}},{"5":{"Elements":[5,6,7,8,9,10,11,12,13,14,15,16,17,0]}},{"2":{"Name":"ServiceAccessPolicyEntry","Properties":{"objectId":{"Type":0,"Flags":1,"Description":"An Azure AD object ID (User or Apps) that is allowed access to the FHIR service."}}}},{"3":{"ItemType":19}},{"2":{"Name":"ServiceCosmosDbConfigurationInfo","Properties":{"offerThroughput":{"Type":22,"Flags":0,"Description":"The provisioned throughput for the backing database."},"keyVaultKeyUri":{"Type":0,"Flags":0,"Description":"The URI of the customer-managed key for the backing database."}}}},{"12":{}},{"2":{"Name":"ServiceAuthenticationConfigurationInfo","Properties":{"authority":{"Type":0,"Flags":0,"Description":"The authority url for the service"},"audience":{"Type":0,"Flags":0,"Description":"The audience url for the service"},"smartProxyEnabled":{"Type":24,"Flags":0,"Description":"If the SMART on FHIR proxy is enabled"}}}},{"11":{}},{"2":{"Name":"ServiceCorsConfigurationInfo","Properties":{"origins":{"Type":26,"Flags":0,"Description":"The origins to be allowed via CORS."},"headers":{"Type":27,"Flags":0,"Description":"The headers to be allowed via CORS."},"methods":{"Type":28,"Flags":0,"Description":"The methods to be allowed via CORS."},"maxAge":{"Type":22,"Flags":0,"Description":"The max age to be allowed via CORS."},"allowCredentials":{"Type":24,"Flags":0,"Description":"If credentials are allowed via CORS."}}}},{"3":{"ItemType":0}},{"3":{"ItemType":0}},{"3":{"ItemType":0}},{"2":{"Name":"ServiceExportConfigurationInfo","Properties":{"storageAccountName":{"Type":0,"Flags":0,"Description":"The name of the default export storage account."}}}},{"2":{"Name":"PrivateEndpointConnection","Properties":{"properties":{"Type":31,"Flags":0,"Description":"Resource properties."},"id":{"Type":0,"Flags":2,"Description":"Fully qualified resource ID for the resource. Ex - /subscriptions/{subscriptionId}/resourceGroups/{resourceGroupName}/providers/{resourceProviderNamespace}/{resourceType}/{resourceName}"},"name":{"Type":0,"Flags":2,"Description":"The name of the resource"},"type":{"Type":0,"Flags":2,"Description":"The type of the resource. E.g. \"Microsoft.Compute/virtualMachines\" or \"Microsoft.Storage/storageAccounts\""}}}},{"2":{"Name":"PrivateEndpointConnectionProperties","Properties":{"privateEndpoint":{"Type":32,"Flags":0,"Description":"The resource of private end point."},"privateLinkServiceConnectionState":{"Type":33,"Flags":1,"Description":"A collection of information about the state of the connection between service consumer and provider."},"provisioningState":{"Type":42,"Flags":2,"Description":"The provisioning state of the private endpoint connection resource."}}}},{"2":{"Name":"PrivateEndpoint","Properties":{"id":{"Type":0,"Flags":2,"Description":"The ARM identifier for Private Endpoint"}}}},{"2":{"Name":"PrivateLinkServiceConnectionState","Properties":{"status":{"Type":37,"Flags":0,"Description":"Indicates whether the connection has been Approved/Rejected/Removed by the owner of the service."},"description":{"Type":0,"Flags":0,"Description":"The reason for approval/rejection of the connection."},"actionsRequired":{"Type":0,"Flags":0,"Description":"A message indicating if changes on the service provider require any updates on the consumer."}}}},{"6":{"Value":"Pending"}},{"6":{"Value":"Approved"}},{"6":{"Value":"Rejected"}},{"5":{"Elements":[34,35,36,0]}},{"6":{"Value":"Succeeded"}},{"6":{"Value":"Creating"}},{"6":{"Value":"Deleting"}},{"6":{"Value":"Failed"}},{"5":{"Elements":[38,39,40,41,0]}},{"3":{"ItemType":30}},{"6":{"Value":"Enabled"}},{"6":{"Value":"Disabled"}},{"5":{"Elements":[44,45,0]}},{"2":{"Name":"ServiceAcrConfigurationInfo","Properties":{"loginServers":{"Type":48,"Flags":0,"Description":"The list of the ACR login servers."},"ociArtifacts":{"Type":50,"Flags":0,"Description":"The list of Open Container Initiative (OCI) artifacts."}}}},{"3":{"ItemType":0}},{"2":{"Name":"ServiceOciArtifactEntry","Properties":{"loginServer":{"Type":0,"Flags":0,"Description":"The Azure Container Registry login server."},"imageName":{"Type":0,"Flags":0,"Description":"The artifact name."},"digest":{"Type":0,"Flags":0,"Description":"The artifact digest."}}}},{"3":{"ItemType":49}},{"2":{"Name":"SystemData","Properties":{"createdBy":{"Type":0,"Flags":0,"Description":"The identity that created the resource."},"createdByType":{"Type":56,"Flags":0,"Description":"The type of identity that created the resource."},"createdAt":{"Type":0,"Flags":0,"Description":"The timestamp of resource creation (UTC)."},"lastModifiedBy":{"Type":0,"Flags":0,"Description":"The identity that last modified the resource."},"lastModifiedByType":{"Type":61,"Flags":0,"Description":"The type of identity that last modified the resource."},"lastModifiedAt":{"Type":0,"Flags":0,"Description":"The timestamp of resource last modification (UTC)"}}}},{"6":{"Value":"User"}},{"6":{"Value":"Application"}},{"6":{"Value":"ManagedIdentity"}},{"6":{"Value":"Key"}},{"5":{"Elements":[52,53,54,55,0]}},{"6":{"Value":"User"}},{"6":{"Value":"Application"}},{"6":{"Value":"ManagedIdentity"}},{"6":{"Value":"Key"}},{"5":{"Elements":[57,58,59,60,0]}},{"6":{"Value":"fhir"}},{"6":{"Value":"fhir-Stu3"}},{"6":{"Value":"fhir-R4"}},{"5":{"Elements":[62,63,64]}},{"2":{"Name":"ServicesResourceTags","Properties":{},"AdditionalProperties":0}},{"2":{"Name":"ServicesResourceIdentity","Properties":{"principalId":{"Type":0,"Flags":2,"Description":"The principal ID of the resource identity."},"tenantId":{"Type":0,"Flags":2,"Description":"The tenant ID of the resource."},"type":{"Type":70,"Flags":0,"Description":"Type of identity being specified, currently SystemAssigned and None are allowed."}}}},{"6":{"Value":"SystemAssigned"}},{"6":{"Value":"None"}},{"5":{"Elements":[68,69,0]}},{"4":{"Name":"Microsoft.HealthcareApis/services@2021-11-01","ScopeType":8,"Body":3,"Flags":0}},{"6":{"Value":"Microsoft.HealthcareApis/services/privateEndpointConnections"}},{"6":{"Value":"2021-11-01"}},{"2":{"Name":"Microsoft.HealthcareApis/services/privateEndpointConnections","Properties":{"id":{"Type":0,"Flags":10,"Description":"The resource id"},"name":{"Type":0,"Flags":9,"Description":"The resource name"},"type":{"Type":72,"Flags":10,"Description":"The resource type"},"apiVersion":{"Type":73,"Flags":10,"Description":"The resource api version"},"properties":{"Type":31,"Flags":0,"Description":"Resource properties."},"systemData":{"Type":51,"Flags":2,"Description":"Metadata pertaining to creation and last modification of the resource."}}}},{"4":{"Name":"Microsoft.HealthcareApis/services/privateEndpointConnections@2021-11-01","ScopeType":8,"Body":74,"Flags":0}},{"6":{"Value":"Microsoft.HealthcareApis/workspaces"}},{"6":{"Value":"2021-11-01"}},{"2":{"Name":"Microsoft.HealthcareApis/workspaces","Properties":{"id":{"Type":0,"Flags":10,"Description":"The resource id"},"name":{"Type":0,"Flags":9,"Description":"The resource name"},"type":{"Type":76,"Flags":10,"Description":"The resource type"},"apiVersion":{"Type":77,"Flags":10,"Description":"The resource api version"},"properties":{"Type":79,"Flags":0,"Description":"Workspaces resource specific properties."},"systemData":{"Type":51,"Flags":2,"Description":"Metadata pertaining to creation and last modification of the resource."},"tags":{"Type":98,"Flags":0,"Description":"Resource tags."},"location":{"Type":0,"Flags":0,"Description":"The resource location."},"etag":{"Type":0,"Flags":0,"Description":"An etag associated with the resource, used for optimistic concurrency when editing it."}}}},{"2":{"Name":"WorkspaceProperties","Properties":{"provisioningState":{"Type":93,"Flags":2,"Description":"The provisioning state."},"privateEndpointConnections":{"Type":94,"Flags":2,"Description":"The list of private endpoint connections that are set up for this resource."},"publicNetworkAccess":{"Type":97,"Flags":0,"Description":"Control permission for data plane traffic coming from public networks while private endpoint is enabled."}}}},{"6":{"Value":"Deleting"}},{"6":{"Value":"Succeeded"}},{"6":{"Value":"Creating"}},{"6":{"Value":"Accepted"}},{"6":{"Value":"Verifying"}},{"6":{"Value":"Updating"}},{"6":{"Value":"Failed"}},{"6":{"Value":"Canceled"}},{"6":{"Value":"Deprovisioned"}},{"6":{"Value":"Moving"}},{"6":{"Value":"Suspended"}},{"6":{"Value":"Warned"}},{"6":{"Value":"SystemMaintenance"}},{"5":{"Elements":[80,81,82,83,84,85,86,87,88,89,90,91,92,0]}},{"3":{"ItemType":30}},{"6":{"Value":"Enabled"}},{"6":{"Value":"Disabled"}},{"5":{"Elements":[95,96,0]}},{"2":{"Name":"ResourceTags","Properties":{},"AdditionalProperties":0}},{"4":{"Name":"Microsoft.HealthcareApis/workspaces@2021-11-01","ScopeType":8,"Body":78,"Flags":0}},{"6":{"Value":"Microsoft.HealthcareApis/workspaces/dicomservices"}},{"6":{"Value":"2021-11-01"}},{"2":{"Name":"Microsoft.HealthcareApis/workspaces/dicomservices","Properties":{"id":{"Type":0,"Flags":10,"Description":"The resource id"},"name":{"Type":0,"Flags":9,"Description":"The resource name"},"type":{"Type":100,"Flags":10,"Description":"The resource type"},"apiVersion":{"Type":101,"Flags":10,"Description":"The resource api version"},"properties":{"Type":103,"Flags":0,"Description":"Dicom Service configuration."},"systemData":{"Type":51,"Flags":2,"Description":"Metadata pertaining to creation and last modification of the resource."},"identity":{"Type":124,"Flags":0,"Description":"Setting indicating whether the service has a managed identity associated with it."},"tags":{"Type":132,"Flags":0,"Description":"Resource tags."},"location":{"Type":0,"Flags":0,"Description":"The resource location."},"etag":{"Type":0,"Flags":0,"Description":"An etag associated with the resource, used for optimistic concurrency when editing it."}}}},{"2":{"Name":"DicomServiceProperties","Properties":{"provisioningState":{"Type":117,"Flags":2,"Description":"The provisioning state."},"authenticationConfiguration":{"Type":118,"Flags":0,"Description":"Dicom Service authentication configuration."},"serviceUrl":{"Type":0,"Flags":2,"Description":"The url of the Dicom Services."},"privateEndpointConnections":{"Type":120,"Flags":2,"Description":"The list of private endpoint connections that are set up for this resource."},"publicNetworkAccess":{"Type":123,"Flags":0,"Description":"Control permission for data plane traffic coming from public networks while private endpoint is enabled."}}}},{"6":{"Value":"Deleting"}},{"6":{"Value":"Succeeded"}},{"6":{"Value":"Creating"}},{"6":{"Value":"Accepted"}},{"6":{"Value":"Verifying"}},{"6":{"Value":"Updating"}},{"6":{"Value":"Failed"}},{"6":{"Value":"Canceled"}},{"6":{"Value":"Deprovisioned"}},{"6":{"Value":"Moving"}},{"6":{"Value":"Suspended"}},{"6":{"Value":"Warned"}},{"6":{"Value":"SystemMaintenance"}},{"5":{"Elements":[104,105,106,107,108,109,110,111,112,113,114,115,116,0]}},{"2":{"Name":"DicomServiceAuthenticationConfiguration","Properties":{"authority":{"Type":0,"Flags":2,"Description":"The authority url for the service"},"audiences":{"Type":119,"Flags":2,"Description":"The audiences for the service"}}}},{"3":{"ItemType":0}},{"3":{"ItemType":30}},{"6":{"Value":"Enabled"}},{"6":{"Value":"Disabled"}},{"5":{"Elements":[121,122,0]}},{"2":{"Name":"ServiceManagedIdentityIdentity","Properties":{"type":{"Type":129,"Flags":1,"Description":"Type of identity being specified, currently SystemAssigned and None are allowed."},"principalId":{"Type":0,"Flags":2,"Description":"The service principal ID of the system assigned identity. This property will only be provided for a system assigned identity."},"tenantId":{"Type":0,"Flags":2,"Description":"The tenant ID of the system assigned identity. This property will only be provided for a system assigned identity."},"userAssignedIdentities":{"Type":131,"Flags":0,"Description":"The set of user assigned identities associated with the resource. The userAssignedIdentities dictionary keys will be ARM resource ids in the form: '/subscriptions/{subscriptionId}/resourceGroups/{resourceGroupName}/providers/Microsoft.ManagedIdentity/userAssignedIdentities/{identityName}. The dictionary values can be empty objects ({}) in requests."}}}},{"6":{"Value":"None"}},{"6":{"Value":"SystemAssigned"}},{"6":{"Value":"UserAssigned"}},{"6":{"Value":"SystemAssigned,UserAssigned"}},{"5":{"Elements":[125,126,127,128,0]}},{"2":{"Name":"UserAssignedIdentity","Properties":{"principalId":{"Type":0,"Flags":2,"Description":"The principal ID of the assigned identity."},"clientId":{"Type":0,"Flags":2,"Description":"The client ID of the assigned identity."}}}},{"2":{"Name":"UserAssignedIdentities","Properties":{},"AdditionalProperties":130}},{"2":{"Name":"ResourceTags","Properties":{},"AdditionalProperties":0}},{"4":{"Name":"Microsoft.HealthcareApis/workspaces/dicomservices@2021-11-01","ScopeType":8,"Body":102,"Flags":0}},{"6":{"Value":"Microsoft.HealthcareApis/workspaces/iotconnectors"}},{"6":{"Value":"2021-11-01"}},{"2":{"Name":"Microsoft.HealthcareApis/workspaces/iotconnectors","Properties":{"id":{"Type":0,"Flags":10,"Description":"The resource id"},"name":{"Type":0,"Flags":9,"Description":"The resource name"},"type":{"Type":134,"Flags":10,"Description":"The resource type"},"apiVersion":{"Type":135,"Flags":10,"Description":"The resource api version"},"properties":{"Type":137,"Flags":0,"Description":"IoT Connector configuration."},"systemData":{"Type":51,"Flags":2,"Description":"Metadata pertaining to creation and last modification of the resource."},"identity":{"Type":124,"Flags":0,"Description":"Setting indicating whether the service has a managed identity associated with it."},"tags":{"Type":155,"Flags":0,"Description":"Resource tags."},"location":{"Type":0,"Flags":0,"Description":"The resource location."},"etag":{"Type":0,"Flags":0,"Description":"An etag associated with the resource, used for optimistic concurrency when editing it."}}}},{"2":{"Name":"IotConnectorProperties","Properties":{"provisioningState":{"Type":151,"Flags":2,"Description":"The provisioning state."},"ingestionEndpointConfiguration":{"Type":152,"Flags":0,"Description":"Source configuration."},"deviceMapping":{"Type":153,"Flags":0,"Description":"Device Mappings."}}}},{"6":{"Value":"Deleting"}},{"6":{"Value":"Succeeded"}},{"6":{"Value":"Creating"}},{"6":{"Value":"Accepted"}},{"6":{"Value":"Verifying"}},{"6":{"Value":"Updating"}},{"6":{"Value":"Failed"}},{"6":{"Value":"Canceled"}},{"6":{"Value":"Deprovisioned"}},{"6":{"Value":"Moving"}},{"6":{"Value":"Suspended"}},{"6":{"Value":"Warned"}},{"6":{"Value":"SystemMaintenance"}},{"5":{"Elements":[138,139,140,141,142,143,144,145,146,147,148,149,150,0]}},{"2":{"Name":"IotEventHubIngestionEndpointConfiguration","Properties":{"eventHubName":{"Type":0,"Flags":0,"Description":"Event Hub name to connect to."},"consumerGroup":{"Type":0,"Flags":0,"Description":"Consumer group of the event hub to connected to."},"fullyQualifiedEventHubNamespace":{"Type":0,"Flags":0,"Description":"Fully qualified namespace of the Event Hub to connect to."}}}},{"2":{"Name":"IotMappingProperties","Properties":{"content":{"Type":154,"Flags":0,"Description":"The mapping."}}}},{"9":{}},{"2":{"Name":"ResourceTags","Properties":{},"AdditionalProperties":0}},{"4":{"Name":"Microsoft.HealthcareApis/workspaces/iotconnectors@2021-11-01","ScopeType":8,"Body":136,"Flags":0}},{"6":{"Value":"Microsoft.HealthcareApis/workspaces/iotconnectors/fhirdestinations"}},{"6":{"Value":"2021-11-01"}},{"2":{"Name":"Microsoft.HealthcareApis/workspaces/iotconnectors/fhirdestinations","Properties":{"id":{"Type":0,"Flags":10,"Description":"The resource id"},"name":{"Type":0,"Flags":9,"Description":"The resource name"},"type":{"Type":157,"Flags":10,"Description":"The resource type"},"apiVersion":{"Type":158,"Flags":10,"Description":"The resource api version"},"properties":{"Type":160,"Flags":1,"Description":"IoT FHIR Destination settings."},"systemData":{"Type":51,"Flags":2,"Description":"Metadata pertaining to creation and last modification of the resource."},"location":{"Type":0,"Flags":0,"Description":"The resource location."},"etag":{"Type":0,"Flags":0,"Description":"An etag associated with the resource, used for optimistic concurrency when editing it."}}}},{"2":{"Name":"IotFhirDestinationProperties","Properties":{"resourceIdentityResolutionType":{"Type":163,"Flags":1,"Description":"Determines how resource identity is resolved on the destination."},"fhirServiceResourceId":{"Type":0,"Flags":1,"Description":"Fully qualified resource id of the FHIR service to connect to."},"fhirMapping":{"Type":153,"Flags":1,"Description":"FHIR Mappings"},"provisioningState":{"Type":177,"Flags":2,"Description":"The provisioning state."}}}},{"6":{"Value":"Create"}},{"6":{"Value":"Lookup"}},{"5":{"Elements":[161,162,0]}},{"6":{"Value":"Deleting"}},{"6":{"Value":"Succeeded"}},{"6":{"Value":"Creating"}},{"6":{"Value":"Accepted"}},{"6":{"Value":"Verifying"}},{"6":{"Value":"Updating"}},{"6":{"Value":"Failed"}},{"6":{"Value":"Canceled"}},{"6":{"Value":"Deprovisioned"}},{"6":{"Value":"Moving"}},{"6":{"Value":"Suspended"}},{"6":{"Value":"Warned"}},{"6":{"Value":"SystemMaintenance"}},{"5":{"Elements":[164,165,166,167,168,169,170,171,172,173,174,175,176,0]}},{"4":{"Name":"Microsoft.HealthcareApis/workspaces/iotconnectors/fhirdestinations@2021-11-01","ScopeType":8,"Body":159,"Flags":0}},{"6":{"Value":"Microsoft.HealthcareApis/workspaces/fhirservices"}},{"6":{"Value":"2021-11-01"}},{"2":{"Name":"Microsoft.HealthcareApis/workspaces/fhirservices","Properties":{"id":{"Type":0,"Flags":10,"Description":"The resource id"},"name":{"Type":0,"Flags":9,"Description":"The resource name"},"type":{"Type":179,"Flags":10,"Description":"The resource type"},"apiVersion":{"Type":180,"Flags":10,"Description":"The resource api version"},"kind":{"Type":184,"Flags":0,"Description":"The kind of the service."},"properties":{"Type":185,"Flags":0,"Description":"Fhir Service configuration."},"systemData":{"Type":51,"Flags":2,"Description":"Metadata pertaining to creation and last modification of the resource."},"identity":{"Type":124,"Flags":0,"Description":"Setting indicating whether the service has a managed identity associated with it."},"tags":{"Type":229,"Flags":0,"Description":"Resource tags."},"location":{"Type":0,"Flags":0,"Description":"The resource location."},"etag":{"Type":0,"Flags":0,"Description":"An etag associated with the resource, used for optimistic concurrency when editing it."}}}},{"6":{"Value":"fhir-Stu3"}},{"6":{"Value":"fhir-R4"}},{"5":{"Elements":[182,183,0]}},{"2":{"Name":"FhirServiceProperties","Properties":{"provisioningState":{"Type":199,"Flags":2,"Description":"The provisioning state."},"accessPolicies":{"Type":201,"Flags":0,"Description":"Fhir Service access policies."},"acrConfiguration":{"Type":202,"Flags":0,"Description":"Fhir Service Azure container registry configuration."},"authenticationConfiguration":{"Type":205,"Flags":0,"Description":"Fhir Service authentication configuration."},"corsConfiguration":{"Type":206,"Flags":0,"Description":"Fhir Service Cors configuration."},"exportConfiguration":{"Type":210,"Flags":0,"Description":"Fhir Service export configuration."},"privateEndpointConnections":{"Type":211,"Flags":2,"Description":"The list of private endpoint connections that are set up for this resource."},"publicNetworkAccess":{"Type":214,"Flags":0,"Description":"Control permission for data plane traffic coming from public networks while private endpoint is enabled."},"eventState":{"Type":218,"Flags":2,"Description":"Fhir Service event support status."},"resourceVersionPolicyConfiguration":{"Type":219,"Flags":0,"Description":"Determines tracking of history for resources."}}}},{"6":{"Value":"Deleting"}},{"6":{"Value":"Succeeded"}},{"6":{"Value":"Creating"}},{"6":{"Value":"Accepted"}},{"6":{"Value":"Verifying"}},{"6":{"Value":"Updating"}},{"6":{"Value":"Failed"}},{"6":{"Value":"Canceled"}},{"6":{"Value":"Deprovisioned"}},{"6":{"Value":"Moving"}},{"6":{"Value":"Suspended"}},{"6":{"Value":"Warned"}},{"6":{"Value":"SystemMaintenance"}},{"5":{"Elements":[186,187,188,189,190,191,192,193,194,195,196,197,198,0]}},{"2":{"Name":"FhirServiceAccessPolicyEntry","Properties":{"objectId":{"Type":0,"Flags":1,"Description":"An Azure AD object ID (User or Apps) that is allowed access to the FHIR service."}}}},{"3":{"ItemType":200}},{"2":{"Name":"FhirServiceAcrConfiguration","Properties":{"loginServers":{"Type":203,"Flags":0,"Description":"The list of the Azure container registry login servers."},"ociArtifacts":{"Type":204,"Flags":0,"Description":"The list of Open Container Initiative (OCI) artifacts."}}}},{"3":{"ItemType":0}},{"3":{"ItemType":49}},{"2":{"Name":"FhirServiceAuthenticationConfiguration","Properties":{"authority":{"Type":0,"Flags":0,"Description":"The authority url for the service"},"audience":{"Type":0,"Flags":0,"Description":"The audience url for the service"},"smartProxyEnabled":{"Type":24,"Flags":0,"Description":"If the SMART on FHIR proxy is enabled"}}}},{"2":{"Name":"FhirServiceCorsConfiguration","Properties":{"origins":{"Type":207,"Flags":0,"Description":"The origins to be allowed via CORS."},"headers":{"Type":208,"Flags":0,"Description":"The headers to be allowed via CORS."},"methods":{"Type":209,"Flags":0,"Description":"The methods to be allowed via CORS."},"maxAge":{"Type":22,"Flags":0,"Description":"The max age to be allowed via CORS."},"allowCredentials":{"Type":24,"Flags":0,"Description":"If credentials are allowed via CORS."}}}},{"3":{"ItemType":0}},{"3":{"ItemType":0}},{"3":{"ItemType":0}},{"2":{"Name":"FhirServiceExportConfiguration","Properties":{"storageAccountName":{"Type":0,"Flags":0,"Description":"The name of the default export storage account."}}}},{"3":{"ItemType":30}},{"6":{"Value":"Enabled"}},{"6":{"Value":"Disabled"}},{"5":{"Elements":[212,213,0]}},{"6":{"Value":"Disabled"}},{"6":{"Value":"Enabled"}},{"6":{"Value":"Updating"}},{"5":{"Elements":[215,216,217,0]}},{"2":{"Name":"ResourceVersionPolicyConfiguration","Properties":{"default":{"Type":223,"Flags":0,"Description":"The default value for tracking history across all resources."},"resourceTypeOverrides":{"Type":228,"Flags":0,"Description":"A list of FHIR Resources and their version policy overrides."}}}},{"6":{"Value":"no-version"}},{"6":{"Value":"versioned"}},{"6":{"Value":"versioned-update"}},{"5":{"Elements":[220,221,222,0]}},{"6":{"Value":"no-version"}},{"6":{"Value":"versioned"}},{"6":{"Value":"versioned-update"}},{"5":{"Elements":[224,225,226,0]}},{"2":{"Name":"ResourceVersionPolicyConfigurationResourceTypeOverrides","Properties":{},"AdditionalProperties":227}},{"2":{"Name":"ResourceTags","Properties":{},"AdditionalProperties":0}},{"4":{"Name":"Microsoft.HealthcareApis/workspaces/fhirservices@2021-11-01","ScopeType":8,"Body":181,"Flags":0}},{"6":{"Value":"Microsoft.HealthcareApis/workspaces/privateEndpointConnections"}},{"6":{"Value":"2021-11-01"}},{"2":{"Name":"Microsoft.HealthcareApis/workspaces/privateEndpointConnections","Properties":{"id":{"Type":0,"Flags":10,"Description":"The resource id"},"name":{"Type":0,"Flags":9,"Description":"The resource name"},"type":{"Type":231,"Flags":10,"Description":"The resource type"},"apiVersion":{"Type":232,"Flags":10,"Description":"The resource api version"},"systemData":{"Type":51,"Flags":2,"Description":"Metadata pertaining to creation and last modification of the resource."},"properties":{"Type":31,"Flags":0,"Description":"Resource properties."}}}},{"4":{"Name":"Microsoft.HealthcareApis/workspaces/privateEndpointConnections@2021-11-01","ScopeType":8,"Body":233,"Flags":0}},{"6":{"Value":"Microsoft.HealthcareApis/services/privateLinkResources"}},{"6":{"Value":"2021-11-01"}},{"2":{"Name":"Microsoft.HealthcareApis/services/privateLinkResources","Properties":{"id":{"Type":0,"Flags":10,"Description":"The resource id"},"name":{"Type":0,"Flags":9,"Description":"The resource name"},"type":{"Type":235,"Flags":10,"Description":"The resource type"},"apiVersion":{"Type":236,"Flags":10,"Description":"The resource api version"},"systemData":{"Type":51,"Flags":2,"Description":"Metadata pertaining to creation and last modification of the resource."},"properties":{"Type":238,"Flags":2,"Description":"Resource properties."}}}},{"2":{"Name":"PrivateLinkResourceProperties","Properties":{"groupId":{"Type":0,"Flags":2,"Description":"The private link resource group id."},"requiredMembers":{"Type":239,"Flags":2,"Description":"The private link resource required member names."},"requiredZoneNames":{"Type":240,"Flags":0,"Description":"The private link resource Private link DNS zone name."}}}},{"3":{"ItemType":0}},{"3":{"ItemType":0}},{"4":{"Name":"Microsoft.HealthcareApis/services/privateLinkResources@2021-11-01","ScopeType":8,"Body":237,"Flags":1}},{"6":{"Value":"Microsoft.HealthcareApis/workspaces/privateLinkResources"}},{"6":{"Value":"2021-11-01"}},{"2":{"Name":"Microsoft.HealthcareApis/workspaces/privateLinkResources","Properties":{"id":{"Type":0,"Flags":10,"Description":"The resource id"},"name":{"Type":0,"Flags":9,"Description":"The resource name"},"type":{"Type":242,"Flags":10,"Description":"The resource type"},"apiVersion":{"Type":243,"Flags":10,"Description":"The resource api version"},"systemData":{"Type":51,"Flags":2,"Description":"Metadata pertaining to creation and last modification of the resource."},"properties":{"Type":238,"Flags":2,"Description":"Resource properties."}}}},{"4":{"Name":"Microsoft.HealthcareApis/workspaces/privateLinkResources@2021-11-01","ScopeType":8,"Body":244,"Flags":1}}]